maldiamrkit/__init__.py
maldiamrkit/py.typed
maldiamrkit/alignment/__init__.py
maldiamrkit/alignment/raw_warping.py
maldiamrkit/alignment/warping.py
maldiamrkit/core/__init__.py
maldiamrkit/core/config.py
maldiamrkit/core/dataset.py
maldiamrkit/core/spectrum.py
maldiamrkit/detection/__init__.py
maldiamrkit/detection/peak_detector.py
maldiamrkit/io/__init__.py
maldiamrkit/io/readers.py
maldiamrkit/preprocessing/__init__.py
maldiamrkit/preprocessing/binning.py
maldiamrkit/preprocessing/pipeline.py
maldiamrkit/preprocessing/quality.py
maldiamrkit/utils/__init__.py
maldiamrkit/utils/plotting.py
maldiamrkit/utils/validation.py
maldiamrkit-0.6.1.dist-info/licenses/LICENSE
maldiamrkit-0.6.1.dist-info/METADATA
maldiamrkit-0.6.1.dist-info/WHEEL
maldiamrkit-0.6.1.dist-info/top_level.txt
maldiamrkit-0.6.1.dist-info/RECORD
