Metadata-Version: 2.4
Name: MaldiAMRKit
Version: 0.6.1
Summary: A comprehensive toolkit for MALDI-TOF mass spectrometry data preprocessing for antimicrobial resistance (AMR) prediction purposes
Author-email: Ettore Rocchi <ettore.rocchi3@unibo.it>
License-Expression: MIT
Project-URL: Homepage, https://github.com/EttoreRocchi/MaldiAMRKit
Project-URL: Documentation, https://github.com/EttoreRocchi/MaldiAMRKit#readme
Project-URL: Source, https://github.com/EttoreRocchi/MaldiAMRKit
Project-URL: Issues, https://github.com/EttoreRocchi/MaldiAMRKit/issues
Keywords: MALDI,MALDI-TOF,mass-spectrometry,machine-learning,AMR,antimicrobial-resistance
Classifier: Development Status :: 3 - Alpha
Classifier: Programming Language :: Python :: 3
Classifier: Programming Language :: Python :: 3.10
Classifier: Programming Language :: Python :: 3.11
Classifier: Programming Language :: Python :: 3.12
Classifier: Intended Audience :: Science/Research
Classifier: Topic :: Scientific/Engineering :: Bio-Informatics
Classifier: Topic :: Scientific/Engineering :: Chemistry
Classifier: Operating System :: OS Independent
Requires-Python: >=3.10
License-File: LICENSE
Requires-Dist: numpy>=1.21.0
Requires-Dist: pandas>=1.3.0
Requires-Dist: scipy>=1.7.0
Requires-Dist: scikit-learn>=1.0.0
Requires-Dist: matplotlib>=3.4.0
Requires-Dist: seaborn>=0.11.0
Requires-Dist: pybaselines>=1.0.0
Requires-Dist: gudhi>=3.5.0
Requires-Dist: fastdtw>=0.3.4
Provides-Extra: docs
Requires-Dist: numpy>=1.21.0; extra == "docs"
Requires-Dist: pandas>=1.3.0; extra == "docs"
Requires-Dist: scipy>=1.7.0; extra == "docs"
Requires-Dist: scikit-learn>=1.0.0; extra == "docs"
Requires-Dist: matplotlib>=3.4.0; extra == "docs"
Requires-Dist: seaborn>=0.11.0; extra == "docs"
Requires-Dist: pybaselines>=1.0.0; extra == "docs"
Requires-Dist: gudhi>=3.5.0; extra == "docs"
Requires-Dist: fastdtw>=0.3.4; extra == "docs"
Requires-Dist: sphinx>=7.0.0; extra == "docs"
Requires-Dist: sphinx-rtd-theme>=2.0.0; extra == "docs"
Requires-Dist: sphinx-autodoc-typehints>=2.0.0; extra == "docs"
Requires-Dist: nbsphinx>=0.9.0; extra == "docs"
Requires-Dist: ipykernel>=6.0.0; extra == "docs"
Provides-Extra: dev
Requires-Dist: pytest>=7.0.0; extra == "dev"
Requires-Dist: pytest-cov>=4.0.0; extra == "dev"
Requires-Dist: ruff>=0.1.0; extra == "dev"
Dynamic: license-file
